{
    "type": "FeatureCollection",
    "name": "estac",
    "crs": {
        "type": "name",
        "properties": {
            "name": "urn:ogc:def:crs:OGC:1.3:CRS84"
        }
    },
    "features": [
        {
            "type": "Feature",
            "properties": {
                "nome_estacao": "LOCG01",
                "data_utc": 1699308540000,
                "temperatura_interna": 73.8,
                "umidade_interna": 69,
                "pressao_relativa_hg": 29.814,
                "pressao_absoluta_hg": 30.142,
                "temperatura": 21.11111111111111,
                "bateria_externa_OK_1_Baixo_0": 1,
                "umidade_externa": 71,
                "direcao_vento": 60,
                "velocidade_vento": 4,
                "velocidade_max_vento_em_10min": 4.5,
                "velocidade_max_vento_no_ultimo_dia": 71,
                "taxa_chuva_por_hora": 0,
                "evento_chuva": 0,
                "chuva_diaria": 0,
                "chuva_mensal": 1.161,
                "chuva_total": 165.083,
                "radiacao_solar_watts_p_m2": 0,
                "ultravioleta": 0,
                "bateria_de_co2_1_ok_0_Baixo": 1,
                "sensacao_termica": 21.133333333333336,
                "ponto_orvalho": 60.15,
                "sensacao_termica_in": 74.1,
                "ponto_orvalho_interno": 61.8,
                "ultima_chuva_por_hora": "2023-11-03T17:01:00.000Z",
                "fuso_horario": "America/Sao_Paulo",
                "data_legivel": "2023-11-06T22:09:00.000Z"
            },
            "geometry": {
                "type": "Point",
                "coordinates": [
                    -48.5419,
                    -25.8175
                ]
            }
        }
    ]
}